topsis102203635/__init__.py
topsis102203635/topsis.py
topsis102203635-0.1.4.dist-info/LICENSE.txt
topsis102203635-0.1.4.dist-info/METADATA
topsis102203635-0.1.4.dist-info/WHEEL
topsis102203635-0.1.4.dist-info/top_level.txt
topsis102203635-0.1.4.dist-info/RECORD
