Metadata-Version: 2.1
Name: topsis102203635
Version: 0.1.4
Summary: Package to perform TOPSIS Analysis
Home-page: https://github.com/DSam327/topsis102203635/
Author: Samrath Singh
Author-email: skharbanda_be22@thapar.edu
Classifier: Programming Language :: Python :: 3
Classifier: License :: OSI Approved :: MIT License
Classifier: Operating System :: OS Independent
Requires-Python: >=3.6
License-File: LICENSE.txt
Requires-Dist: pandas
Requires-Dist: numpy
